xchainpy2_thorchain_query/__init__.py
xchainpy2_thorchain_query/cache.py
xchainpy2_thorchain_query/const.py
xchainpy2_thorchain_query/env.py
xchainpy2_thorchain_query/fee.py
xchainpy2_thorchain_query/liquidity.py
xchainpy2_thorchain_query/midgard.py
xchainpy2_thorchain_query/models.py
xchainpy2_thorchain_query/patch_clients.py
xchainpy2_thorchain_query/query.py
xchainpy2_thorchain_query/swap.py
xchainpy2_thorchain_query/thornode.py
xchainpy2_thorchain_query/tests/__init__.py
xchainpy2_thorchain_query/tests/common.py
xchainpy2_thorchain_query/tests/test_estimate_thor_name.py
xchainpy2_thorchain_query/tests/test_math.py
xchainpy2_thorchain_query/tests/test_thor_name_cache.py
xchainpy2_thorchain_query/tests/test_timeout.py
xchainpy2_thorchain_query/tests/mock_data/inbound_addresses.json
xchainpy2_thorchain_query/tests/mock_data/lastblock.json
xchainpy2_thorchain_query/tests/mock_data/midgard_pools.json
xchainpy2_thorchain_query/tests/mock_data/midgard_t_name.json
xchainpy2_thorchain_query/tests/mock_data/thornode_pools.json
xchainpy2_thorchain_query/track/__init__.py
xchainpy2_thorchain_query/track/dtypes.py
xchainpy2_thorchain_query/track/tracker.py
xchainpy2_thorchain_query-0.0.31.dist-info/METADATA
xchainpy2_thorchain_query-0.0.31.dist-info/WHEEL
xchainpy2_thorchain_query-0.0.31.dist-info/top_level.txt
xchainpy2_thorchain_query-0.0.31.dist-info/RECORD
